promulgate/__init__.py
promulgate/py.typed
promulgate-0.1.2.dist-info/WHEEL
promulgate-0.1.2.dist-info/METADATA
promulgate-0.1.2.dist-info/RECORD
