Metadata-Version: 2.1
Name: promulgate
Version: 0.1.2
License: MIT
Author-email: Christian Kranemann <cpkranemann@gmail.com>
Requires-Python: >=3.11
